MANIFEST.in
setup.py
./__init__.py
./__openerp__.py
i18n/ar.po
i18n/bg.po
i18n/bn.po
i18n/bs.po
i18n/ca.po
i18n/cs.po
i18n/da.po
i18n/de.po
i18n/en_AU.po
i18n/en_GB.po
i18n/es.po
i18n/es_CL.po
i18n/es_CR.po
i18n/es_DO.po
i18n/es_EC.po
i18n/es_MX.po
i18n/es_PE.po
i18n/et.po
i18n/eu.po
i18n/fa.po
i18n/fi.po
i18n/fr.po
i18n/fr_CA.po
i18n/gl.po
i18n/gu.po
i18n/hr.po
i18n/hu.po
i18n/id.po
i18n/it.po
i18n/ja.po
i18n/ka.po
i18n/ko.po
i18n/lt.po
i18n/mk.po
i18n/mn.po
i18n/nb.po
i18n/nl.po
i18n/nl_BE.po
i18n/pl.po
i18n/pt.po
i18n/pt_BR.po
i18n/ro.po
i18n/ru.po
i18n/sk.po
i18n/sl.po
i18n/sq.po
i18n/sr@latin.po
i18n/sv.po
i18n/th.po
i18n/tr.po
i18n/uk.po
i18n/web_calendar.pot
i18n/zh_CN.po
i18n/zh_TW.po
openerp_web_calendar.egg-info/PKG-INFO
openerp_web_calendar.egg-info/SOURCES.txt
openerp_web_calendar.egg-info/dependency_links.txt
openerp_web_calendar.egg-info/requires.txt
openerp_web_calendar.egg-info/top_level.txt
static/lib/dhtmlxScheduler/codebase/imgs/but_repeat.gif
static/lib/dhtmlxScheduler/codebase/imgs/buttons.png
static/lib/dhtmlxScheduler/codebase/imgs/calendar.gif
static/lib/dhtmlxScheduler/codebase/imgs/clock_big.gif
static/lib/dhtmlxScheduler/codebase/imgs/clock_small.gif
static/lib/dhtmlxScheduler/codebase/imgs/collapse_expand_icon.gif
static/lib/dhtmlxScheduler/codebase/imgs/controls.gif
static/lib/dhtmlxScheduler/codebase/imgs/databg.png
static/lib/dhtmlxScheduler/codebase/imgs/databg_now.png
static/lib/dhtmlxScheduler/codebase/imgs/icon.png
static/lib/dhtmlxScheduler/codebase/imgs/images.png
static/lib/dhtmlxScheduler/codebase/imgs/loading.gif
static/lib/dhtmlxScheduler/codebase/imgs/resize_dots.png
static/lib/dhtmlxScheduler/codebase/imgs_dhx_terrace/arrow_left.png
static/lib/dhtmlxScheduler/codebase/imgs_dhx_terrace/arrow_right.png
static/lib/dhtmlxScheduler/codebase/imgs_dhx_terrace/but_repeat.gif
static/lib/dhtmlxScheduler/codebase/imgs_dhx_terrace/calendar.gif
static/lib/dhtmlxScheduler/codebase/imgs_dhx_terrace/clock_big.gif
static/lib/dhtmlxScheduler/codebase/imgs_dhx_terrace/clock_small.gif
static/lib/dhtmlxScheduler/codebase/imgs_dhx_terrace/close_icon.png
static/lib/dhtmlxScheduler/codebase/imgs_dhx_terrace/collapse_expand_icon.gif
